openctp_ctp_cp/thostmduserapi.py
openctp_ctp_cp/thostmduserapi_se.dll
openctp_ctp_cp/thosttraderapi.py
openctp_ctp_cp/thosttraderapi_se.dll
openctp_ctp_cp/_thostmduserapi.pyd
openctp_ctp_cp/_thosttraderapi.pyd
openctp_ctp_cp/__init__.py
openctp_ctp_cp-6.7.7.0.dist-info/DELVEWHEEL
openctp_ctp_cp-6.7.7.0.dist-info/LICENSE
openctp_ctp_cp-6.7.7.0.dist-info/METADATA
openctp_ctp_cp-6.7.7.0.dist-info/RECORD
openctp_ctp_cp-6.7.7.0.dist-info/top_level.txt
openctp_ctp_cp-6.7.7.0.dist-info/WHEEL
openctp_ctp_cp.libs/msvcp140-7d86b013b282849779eafe132d7f80f0.dll
openctp_ctp_cp.libs/thostmduserapi_se-460c298dd5732bce555c427ca282985d.dll
openctp_ctp_cp.libs/thosttraderapi_se-535711e64151053703bbef3e9784cb3e.dll
